euler/__init__.py
euler/__main__.py
euler/euler.py
euler/test_euler.py
euler_cli-0.1.2.dist-info/METADATA
euler_cli-0.1.2.dist-info/WHEEL
euler_cli-0.1.2.dist-info/entry_points.txt
euler_cli-0.1.2.dist-info/top_level.txt
euler_cli-0.1.2.dist-info/RECORD
